pipelines_insights/__init__.py
pipelines_insights/pipelines.py
pipelines_insights/utils.py
pipelines_insights-0.0.1.dist-info/LICENSE
pipelines_insights-0.0.1.dist-info/METADATA
pipelines_insights-0.0.1.dist-info/WHEEL
pipelines_insights-0.0.1.dist-info/top_level.txt
pipelines_insights-0.0.1.dist-info/RECORD
