Metadata-Version: 2.1
Name: pipelines-insights
Version: 0.0.1
Author-email: Enzo Conejero <enzoconejero0@gmail.com>
Project-URL: Homepage, https://github.com/enzoconejero/pipelines-insights
Classifier: Development Status :: 1 - Planning
Classifier: License :: OSI Approved :: GNU General Public License v3 (GPLv3)
Classifier: Operating System :: OS Independent
Classifier: Programming Language :: Python :: 3
Requires-Python: >3.7
License-File: LICENSE
Requires-Dist: PyYAML ==6.0.1
